biobuntu-1.2.4.dist-info/licenses/LICENSE
cli/__init__.py
cli/cli.py
configs/__init__.py
configs/default.yaml
configs/threads.yaml
configs/tools.yaml
core/__init__.py
core/config.py
core/engine.py
core/file_manager.py
core/logger.py
core/project_manager.py
core/runner.py
core/utils.py
gui/__init__.py
gui/main.py
gui/widgets/file_drop.py
gui/widgets/progress_bar.py
gui/windows/main_window.py
gui/windows/settings_window.py
tools/bwa.py
tools/fastqc.py
tools/gatk.py
tools/hisat2.py
tools/samtools.py
web/__init__.py
web/api.py
web/routes/__init__.py
web/routes/pipelines.py
web/routes/projects.py
web/routes/status.py
web/static/css/style.css
web/static/images/favicon.svg
web/static/images/logo.svg
web/static/images/spinner.svg
web/static/js/app.js
web/templates/index.html
biobuntu-1.2.4.dist-info/METADATA
biobuntu-1.2.4.dist-info/WHEEL
biobuntu-1.2.4.dist-info/entry_points.txt
biobuntu-1.2.4.dist-info/top_level.txt
biobuntu-1.2.4.dist-info/RECORD
