Metadata-Version: 2.4
Name: biobuntu
Version: 1.2.4
Summary: A comprehensive platform for running genomic analysis pipelines with CLI, GUI, and web interfaces. Perfect for researchers, labs, and bioinformatics teams.
Author-email: BioBuntu <info@biobuntu.com>
License-Expression: MIT
Project-URL: Homepage, https://biobuntu.github.io/
Project-URL: Source, https://github.com/biobuntu/biobuntu
Project-URL: Tracker, https://github.com/biobuntu/biobuntu/issues
Project-URL: Documentation, https://biobuntu.github.io/docs
Keywords: bioinformatics,genomics,pipelines,workflow,cli,gui,web
Classifier: Programming Language :: Python :: 3
Classifier: Operating System :: OS Independent
Requires-Python: >=3.8
License-File: LICENSE
Requires-Dist: click
Requires-Dist: pyyaml
Requires-Dist: flask
Dynamic: license-file
